Metadata-Version: 2.1
Name: Notipyer
Version: 0.4.0
Summary: Notification Triggers for Python
Home-page: https://github.com/chirag-jn/notipyer
Author: Chirag Jain
Classifier: Programming Language :: Python :: 3
Classifier: Operating System :: OS Independent
Requires-Python: >=3.6
License-File: LICENSE
